smart_signals/__init__.py
smart_signals/smart_signals.py
SmartSignals-0.2.0.dist-info/LICENSE.txt
SmartSignals-0.2.0.dist-info/METADATA
SmartSignals-0.2.0.dist-info/WHEEL
SmartSignals-0.2.0.dist-info/top_level.txt
SmartSignals-0.2.0.dist-info/RECORD
