Metadata-Version: 2.1
Name: SmartSignals
Version: 0.2.0
Summary: The SmartSignal lib is an event driven system similar to QT.
Home-page: https://github.com/grobbles/SmartSignals
Author: Uwe Roder
Author-email: uweroder@gmail.com
License: MIT
Keywords: smart_signals,SmartSignals,signals,events,slot,qt
Classifier: Development Status :: 3 - Alpha
Classifier: License :: OSI Approved :: MIT License
Classifier: Intended Audience :: Developers
Classifier: Topic :: Communications
Classifier: Topic :: Utilities
Classifier: Programming Language :: Python
Classifier: Programming Language :: Python :: 3.7
Classifier: Programming Language :: Python :: 3.8
Classifier: Programming Language :: Python :: 3.9
Classifier: Programming Language :: Python :: 3.10
Requires-Python: >=3.7
License-File: LICENSE.txt
Requires-Dist: flake8
Requires-Dist: pytest
Requires-Dist: pytest-cov
Requires-Dist: coverage
